xhtml/__init__.py
xhtml/attribute.py
xhtml/element/__init__.py
xhtml/element/attr.py
xhtml/element/css.py
xhtml/element/doc.py
xhtml/element/tag.py
xhtml/header/__init__.py
xhtml/header/accept.py
xhtml/header/authorization.py
xhtml/header/content.py
xhtml/header/cookie.py
xhtml/header/headers.py
xhtml/locale/__init__.py
xhtml/locale/template.py
xhtml/resource/__init__.py
xhtml/resource/favicon.ico
xhtml/resource/logo.svg
xhtml/template/__init__.py
xhtml/template/hello.html
xhtm-0.12.1.dist-info/LICENSE
xhtm-0.12.1.dist-info/METADATA
xhtm-0.12.1.dist-info/WHEEL
xhtm-0.12.1.dist-info/top_level.txt
xhtm-0.12.1.dist-info/zip-safe
xhtm-0.12.1.dist-info/RECORD
