Metadata-Version: 2.1
Name: xhtm
Version: 0.12.1
Summary: Rendering HTML Text
Home-page: https://github.com/bondbox/xhtm
Author: Mingzhe Zou
Author-email: zoumingzhe@outlook.com
License: GPLv2
Project-URL: Source Code, https://github.com/bondbox/xhtm
Project-URL: Bug Tracker, https://github.com/bondbox/issues
Project-URL: Documentation, https://github.com/bondbox/xhtm
Keywords: command-line,argparse,argcomplete
Platform: any
Classifier: Programming Language :: Python
Classifier: Programming Language :: Python :: 3
Requires-Python: >=3.8
License-File: LICENSE
Requires-Dist: xkits-lib >=0.4
Requires-Dist: xlc >=1.1
Requires-Dist: jinja2
